shopiuu_api/ShopiuuClient.py
shopiuu_api/__init__.py
shopiuu_api/Core/Result.py
shopiuu_api/Core/ShopiuuException.py
shopiuu_api/Core/__init__.py
shopiuu_api/Http/ErrorResponse.py
shopiuu_api/Http/RequestCore.py
shopiuu_api/Http/RequestException.py
shopiuu_api/Http/ResponseCore.py
shopiuu_api/Http/__init__.py
shopiuu_api/Model/Article.py
shopiuu_api/Model/ArticleCategory.py
shopiuu_api/Model/Currency.py
shopiuu_api/Model/EmbedCode.py
shopiuu_api/Model/Model.py
shopiuu_api/Model/Nav.py
shopiuu_api/Model/Payment.py
shopiuu_api/Model/Product.py
shopiuu_api/Model/Seo.py
shopiuu_api/Model/Settings.py
shopiuu_api/Model/Shipping.py
shopiuu_api/Model/ShippingArea.py
shopiuu_api/Model/ShippingCompany.py
shopiuu_api/Model/StoreTheme.py
shopiuu_api/Model/__init__.py
shopiuu_api-0.0.2.dist-info/METADATA
shopiuu_api-0.0.2.dist-info/WHEEL
shopiuu_api-0.0.2.dist-info/licenses/LICENSE
shopiuu_api-0.0.2.dist-info/RECORD
